twomodalbert/DataPreparation.py
twomodalbert/Dataset.py
twomodalbert/Inference.py
twomodalbert/Model.py
twomodalbert/Trainer.py
twomodalbert/__init__.py
twomodalbert-0.0.1.dist-info/METADATA
twomodalbert-0.0.1.dist-info/WHEEL
twomodalbert-0.0.1.dist-info/licenses/LICENSE
twomodalbert-0.0.1.dist-info/RECORD
