Metadata-Version: 2.1
Name: twomodalbert
Version: 0.0.1
Summary: A package to build neural networks based on two separate text fields.
Project-URL: Homepage, https://github.com/zuzadeu/twomodalbert
Project-URL: Bug Tracker, https://github.com/zuzadeu/twomodalbert/issues
Author-email: Zuzanna Deutschman <zuza.deu@gmail.com>
License-File: LICENSE
Classifier: License :: OSI Approved :: MIT License
Classifier: Operating System :: OS Independent
Classifier: Programming Language :: Python :: 3
Requires-Python: >=3.7
